geode_viewables/__init__.py
geode_viewables/__init__.pyi
geode_viewables/conversion.py
geode_viewables/conversion.pyi
geode_viewables/py.typed
geode_viewables/qem_proxy.py
geode_viewables/qem_proxy.pyi
geode_viewables/bin/Geode-Viewables_conversion.dll
geode_viewables/bin/Geode-Viewables_qem_proxy.dll
geode_viewables/bin/__init__.pyi
geode_viewables/bin/geode_viewables_py_conversion.cp312-win_amd64.pyd
geode_viewables/bin/geode_viewables_py_conversion.pyi
geode_viewables/bin/geode_viewables_py_qem_proxy.cp312-win_amd64.pyd
geode_viewables/bin/geode_viewables_py_qem_proxy.pyi
geode_viewables-3.3.2.dist-info/METADATA
geode_viewables-3.3.2.dist-info/WHEEL
geode_viewables-3.3.2.dist-info/top_level.txt
geode_viewables-3.3.2.dist-info/RECORD
