Metadata-Version: 2.4
Name: Geode-Viewables
Version: 3.3.2
Summary: Geode module to objects visualization
Author-email: Geode-solutions <contact@geode-solutions.com>
License: Proprietary
Requires-Python: <3.13,>=3.9
Requires-Dist: geode-common==33.*,>=33.11.3
Requires-Dist: opengeode-core==15.*,>=15.29.0
Requires-Dist: opengeode-geosciences==9.*,>=9.5.0
Requires-Dist: opengeode-io==7.*,>=7.4.1
